LICENSE
MANIFEST.in
README.rst
requirements.txt
setup.py
bin/ugly
ugly/__init__.py
ugly/app.py
ugly/config.py
ugly/feed.py
ugly.egg-info/PKG-INFO
ugly.egg-info/SOURCES.txt
ugly.egg-info/dependency_links.txt
ugly.egg-info/requires.txt
ugly.egg-info/top_level.txt