Metadata-Version: 1.1
Name: ugly
Version: 0.0.2
Summary: Fucking ugly RSS
Home-page: https://github.com/dfm/ugly
Author: Dan F-M
Author-email: danfm@nyu.edu
License: MIT
Platform: UNKNOWN
Classifier: Development Status :: 3 - Alpha
Classifier: License :: OSI Approved :: MIT License
Classifier: Programming Language :: Python :: 3.3
